qris_payment/__init__.py
qris_payment/payment_checker.py
qris_payment/qr_generator.py
qris_payment-1.2.0.dist-info/METADATA
qris_payment-1.2.0.dist-info/WHEEL
qris_payment-1.2.0.dist-info/top_level.txt
qris_payment-1.2.0.dist-info/RECORD
