Metadata-Version: 2.4
Name: qris-payment
Version: 1.2.0
Summary: Package Python untuk generate QRIS dan cek status pembayaran dengan URL mutasi yang dapat dikonfigurasi
Home-page: https://github.com/AutoFtBot/qris-payment-py
Author: AutoFtBot
Author-email: autoftbot@gmail.com
Classifier: Programming Language :: Python :: 3
Classifier: License :: OSI Approved :: MIT License
Classifier: Operating System :: OS Independent
Requires-Python: >=3.6
Requires-Dist: qrcode>=7.4.2
Requires-Dist: Pillow>=9.0.0
Requires-Dist: requests>=2.28.0
Dynamic: author
Dynamic: author-email
Dynamic: classifier
Dynamic: description
Dynamic: description-content-type
Dynamic: home-page
Dynamic: requires-dist
Dynamic: requires-python
Dynamic: summary
